codeguard/__init__.py
codeguard/__main__.py
codeguard/config.py
codeguard/version.py
codeguard/ai_ownership/__init__.py
codeguard/ai_ownership/config_parser.py
codeguard/ai_ownership/p2p_bridge.py
codeguard/chat/__init__.py
codeguard/chat/prompt/__init__.py
codeguard/chat/prompt/prompt_plugin.py
codeguard/chat/shared/__init__.py
codeguard/chat/shared/cli_bridge.py
codeguard/chat/sys/__init__.py
codeguard/chat/sys/sys_plugin.py
codeguard/cli/__init__.py
codeguard/cli/cli.py
codeguard/cli/cli_typer.py
codeguard/cli/cli_utils.py
codeguard/cli/p2p_integration.py
codeguard/cli/script_loader.py
codeguard/cli/worker_service.py
codeguard/cli/commands/__init__.py
codeguard/cli/commands/acl.py
codeguard/cli/commands/config.py
codeguard/cli/commands/context_scanner.py
codeguard/cli/commands/directory_guards.py
codeguard/cli/commands/display_engine.py
codeguard/cli/commands/file_commands.py
codeguard/cli/commands/p2p.py
codeguard/cli/commands/prompt_inject.py
codeguard/cli/commands/server.py
codeguard/cli/commands/setup.py
codeguard/cli/commands/smart_notes.py
codeguard/cli/commands/ssl.py
codeguard/cli/commands/sys.py
codeguard/cli/commands/themes.py
codeguard/cli/commands/tui_command.py
codeguard/cli/commands/wrap.py
codeguard/cli/components/__init__.py
codeguard/cli/components/display.py
codeguard/cli/components/parser.py
codeguard/context/__init__.py
codeguard/context/cache_integration.py
codeguard/context/models.py
codeguard/context/modules.py
codeguard/context/ownership.py
codeguard/context/scanner.py
codeguard/context/analysis/__init__.py
codeguard/context/analysis/refactor_scoring.py
codeguard/context/analyzers/__init__.py
codeguard/context/analyzers/breadth_scanner.py
codeguard/context/analyzers/dependency_analyzer.py
codeguard/context/analyzers/static_analyzer.py
codeguard/context/changes/__init__.py
codeguard/context/changes/change_detector.py
codeguard/context/changes/impact_analyzer.py
codeguard/context/changes/update_strategy.py
tumee_codeguard-0.26.1.dist-info/licenses/LICENSE
tumee_codeguard-0.26.1.dist-info/METADATA
tumee_codeguard-0.26.1.dist-info/WHEEL
tumee_codeguard-0.26.1.dist-info/entry_points.txt
tumee_codeguard-0.26.1.dist-info/top_level.txt
tumee_codeguard-0.26.1.dist-info/RECORD
