Metadata-Version: 2.4
Name: tumee-codeguard
Version: 0.26.1
Summary: A code validation tool for enforcing access control on code modifications
Author-email: TuMee Dev <it@tumee.com>
Maintainer-email: TuMee Dev <it@tumee.com>
License-Expression: MIT
Project-URL: Homepage, https://github.com/TuMee-Dev/TuMee-Code-Validator
Project-URL: Repository, https://github.com/TuMee-Dev/TuMee-Code-Validator
Project-URL: Issues, https://github.com/TuMee-Dev/TuMee-Code-Validator/issues
Classifier: Development Status :: 3 - Alpha
Classifier: Intended Audience :: Developers
Classifier: Programming Language :: Python :: 3
Classifier: Programming Language :: Python :: 3.8
Classifier: Programming Language :: Python :: 3.9
Classifier: Programming Language :: Python :: 3.10
Classifier: Programming Language :: Python :: 3.11
Classifier: Programming Language :: Python :: 3.12
Requires-Python: >=3.8
License-File: LICENSE
Requires-Dist: tree-sitter<0.24.0,>=0.23.0
Requires-Dist: tree-sitter-python<0.24.0,>=0.21.0
Requires-Dist: tree-sitter-javascript<0.24.0,>=0.21.0
Requires-Dist: tree-sitter-typescript<0.24.0,>=0.21.0
Requires-Dist: tree-sitter-java<0.24.0,>=0.21.0
Requires-Dist: tree-sitter-c-sharp<0.24.0,>=0.21.0
Requires-Dist: tree-sitter-cpp<0.24.0,>=0.21.0
Requires-Dist: tree-sitter-go<0.24.0,>=0.21.0
Requires-Dist: tree-sitter-rust<0.23.0,>=0.21.0
Requires-Dist: tree-sitter-ruby<0.24.0,>=0.21.0
Requires-Dist: tree-sitter-php<0.24.0,>=0.21.0
Requires-Dist: tree-sitter-html<0.24.0,>=0.20.0
Requires-Dist: tree-sitter-css<0.24.0,>=0.21.0
Requires-Dist: tree-sitter-bash<0.24.0,>=0.21.0
Requires-Dist: tree-sitter-sql<0.4.0,>=0.3.0
Requires-Dist: tree-sitter-json<0.25.0,>=0.24.0
Requires-Dist: tree-sitter-yaml<0.8.0,>=0.7.0
Requires-Dist: tree-sitter-toml<0.8.0,>=0.7.0
Requires-Dist: tree-sitter-lua<0.3.0,>=0.2.0
Requires-Dist: tree-sitter-scala<0.24.0,>=0.21.0
Requires-Dist: tree-sitter-haskell<0.24.0,>=0.21.0
Requires-Dist: tree-sitter-ocaml<0.25.0,>=0.21.0
Requires-Dist: tree-sitter-markdown<0.4.0,>=0.3.0
Requires-Dist: pathspec>=0.11.0
Requires-Dist: pyyaml>=6.0
Requires-Dist: colorama>=0.4.6
Requires-Dist: typer>=0.16.0
Requires-Dist: rich>=13.0.0
Requires-Dist: textual>=0.41.0
Requires-Dist: fastapi==0.115.12
Requires-Dist: fastmcp==2.6.0
Requires-Dist: fastapi-mcp==0.3.4
Requires-Dist: mcp==1.9.2
Requires-Dist: uvicorn==0.25.0
Requires-Dist: diskcache==5.6.3
Requires-Dist: cachetools==5.3.0
Requires-Dist: redis==5.0.1
Requires-Dist: httpx>=0.25.0
Requires-Dist: sse-starlette>=1.6.0
Requires-Dist: pydantic>=2.0.0
Requires-Dist: litellm>=1.40.0
Requires-Dist: proxy.py>=2.4.0
Requires-Dist: cryptography>=41.0.0
Requires-Dist: pyopenssl>=23.0.0
Requires-Dist: watchdog>=3.0.0
Requires-Dist: aiofiles>=23.0.0
Requires-Dist: aioconsole>=0.6.0
Requires-Dist: aiopath>=0.6.11
Requires-Dist: lz4>=4.0.0
Requires-Dist: pyzmq>=25.0.0
Requires-Dist: psutil>=5.9.0
Requires-Dist: dart-tools>=0.7.2
Provides-Extra: dev
Requires-Dist: pytest>=8.0.0; extra == "dev"
Requires-Dist: pytest-asyncio>=0.23.0; extra == "dev"
Requires-Dist: pytest-cov>=4.1.0; extra == "dev"
Requires-Dist: black>=24.0.0; extra == "dev"
Requires-Dist: flake8>=7.0.0; extra == "dev"
Requires-Dist: mypy>=1.8.0; extra == "dev"
Requires-Dist: isort>=5.13.0; extra == "dev"
Requires-Dist: twine>=4.0.2; extra == "dev"
Requires-Dist: build>=1.0.0; extra == "dev"
Dynamic: license-file
